jupyterlab_sos/__init__.py
jupyterlab_sos/_version.py
jupyterlab_sos-0.11.0.data/data/share/jupyter/labextensions/jupyterlab-sos/package.json
jupyterlab_sos-0.11.0.data/data/share/jupyter/labextensions/jupyterlab-sos/schemas/jupyterlab-sos/package.json.orig
jupyterlab_sos-0.11.0.data/data/share/jupyter/labextensions/jupyterlab-sos/schemas/jupyterlab-sos/plugin.json
jupyterlab_sos-0.11.0.data/data/share/jupyter/labextensions/jupyterlab-sos/static/576.a3658dd9a17f71a759ef.js
jupyterlab_sos-0.11.0.data/data/share/jupyter/labextensions/jupyterlab-sos/static/660.14739b548f01e481e862.js
jupyterlab_sos-0.11.0.data/data/share/jupyter/labextensions/jupyterlab-sos/static/728.10bfed8169c209af0b7f.js
jupyterlab_sos-0.11.0.data/data/share/jupyter/labextensions/jupyterlab-sos/static/remoteEntry.c7da854c11b62175fc02.js
jupyterlab_sos-0.11.0.data/data/share/jupyter/labextensions/jupyterlab-sos/static/style.js
jupyterlab_sos-0.11.0.data/data/share/jupyter/labextensions/jupyterlab-sos/static/third-party-licenses.json
jupyterlab_sos-0.11.0.data/data/share/jupyter/labextensions/jupyterlab-sos/install.json
jupyterlab_sos-0.11.0.dist-info/METADATA
jupyterlab_sos-0.11.0.dist-info/WHEEL
jupyterlab_sos-0.11.0.dist-info/licenses/LICENSE
jupyterlab_sos-0.11.0.dist-info/RECORD
