Metadata-Version: 2.3
Name: jupyterlab_sos
Version: 0.11.0
Dynamic: Keywords
Summary: JupyterLab extension for SoS workflow engine and polyglot notebook
Project-URL: Homepage, https://github.com/vatlab/jupyterlab-sos
Project-URL: Bug Tracker, https://github.com/vatlab/jupyterlab-sos/issues
Project-URL: Repository, https://github.com/vatlab/jupyterlab-sos.git
Author-email: Bo Peng <ben.bob@gmail.com>
License: BSD 3-Clause License
License-File: LICENSE
Classifier: Framework :: Jupyter
Classifier: Framework :: Jupyter :: JupyterLab
Classifier: Framework :: Jupyter :: JupyterLab :: 4
Classifier: Framework :: Jupyter :: JupyterLab :: Extensions
Classifier: Framework :: Jupyter :: JupyterLab :: Extensions :: Prebuilt
Classifier: License :: OSI Approved :: BSD License
Classifier: Programming Language :: Python
Classifier: Programming Language :: Python :: 3
Classifier: Programming Language :: Python :: 3.8
Classifier: Programming Language :: Python :: 3.9
Classifier: Programming Language :: Python :: 3.10
Classifier: Programming Language :: Python :: 3.11
Classifier: Programming Language :: Python :: 3.12
Requires-Python: >=3.8
Requires-Dist: jupyterlab>=4.2.0
Requires-Dist: sos
Requires-Dist: sos-notebook
Requires-Dist: transient-display-data
